README.rst
setup.py
EPP.egg-info/PKG-INFO
EPP.egg-info/SOURCES.txt
EPP.egg-info/dependency_links.txt
EPP.egg-info/requires.txt
EPP.egg-info/top_level.txt
eppy/__init__.py
eppy/childorder.py
eppy/client.py
eppy/constants.py
eppy/doc.py
eppy/exceptions.py
eppy/utils.py
eppy/xmldict.py