Metadata-Version: 1.0
Name: EPP
Version: 0.9.1
Summary: EPP Client for Python
Home-page: UNKNOWN
Author: Wil Tan
Author-email: wil@cloudregistry.net
License: MIT/X
Platform: UNKNOWN
